ondemandutils/__init__.py
ondemandutils/editors/__init__.py
ondemandutils/editors/_editor.py
ondemandutils/editors/nginx_stage.py
ondemandutils/editors/ood_portal.py
ondemandutils/models/__init__.py
ondemandutils/models/_model.py
ondemandutils/models/_options.py
ondemandutils/models/nginx_stage.py
ondemandutils/models/ood_portal.py
ondemandutils-0.2.0.dist-info/LICENSE
ondemandutils-0.2.0.dist-info/METADATA
ondemandutils-0.2.0.dist-info/WHEEL
ondemandutils-0.2.0.dist-info/RECORD
