Metadata-Version: 2.1
Name: ondemandutils
Version: 0.2.0
Summary: Utilities and APIs for orchestrating the Open Ondemand deployment lifecycle.
Home-page: https://github.com/charmed-hpc/ondemandutils
License: LGPL-3.0-only
Keywords: HPC,administration,orchestration,utility
Author: Jason C. Nucciarone
Author-email: nuccitheboss@ubuntu.com
Maintainer: Jason C. Nucciarone
Maintainer-email: nuccitheboss@ubuntu.com
Requires-Python: >=3.8
Classifier: Development Status :: 3 - Alpha
Classifier: Intended Audience :: Developers
Classifier: Intended Audience :: Science/Research
Classifier: License :: OSI Approved :: GNU Lesser General Public License v3 (LGPLv3)
Classifier: Operating System :: POSIX :: Linux
Classifier: Programming Language :: Python :: 3
Classifier: Programming Language :: Python :: 3.8
Classifier: Programming Language :: Python :: 3.9
Classifier: Programming Language :: Python :: 3.10
Classifier: Programming Language :: Python :: 3.11
Requires-Dist: pyyaml (==6.0.1)
Project-URL: Bug Tracker, https://github.com/charmed-hpc/ondemandutils/issues
Project-URL: Repository, https://github.com/charmed-hpc/ondemandutils
